[
  {
    "attachments":
    [
      "https://64.media.tumblr.com/cfdd999bd776235a6ec3380efef43acf/cc115a61da0b497c-6d/s640x960/a1e23fab9af00d5be8b3272129c27b2416d83cf4.jpg"
    ],
    "uid": "https://kimchicuddles.com/post/723178560871907328",
    "link": "https://kimchicuddles.com/post/723178560871907328",
    "published_at": "2023-07-18 06:40:19 -0400",
    "text": "https://kimchicuddles.com/post/723178560871907328",
    "comments":
    [],
    "validation_errors":
    []
  },
  {
    "attachments":
    [
      "https://64.media.tumblr.com/1bf23e4d265cdfca0b074844e7dca2e7/0494c8b545d20b74-ce/s640x960/88e398763f9698ab0aab2bdec401998cf1cf00f3.jpg"
    ],
    "comments":
    [],
    "link": "https://kimchicuddles.com/post/721919876659363840",
    "published_at": "2023-07-04 09:14:04 -0400",
    "text": "https://kimchicuddles.com/post/721919876659363840",
    "uid": "https://kimchicuddles.com/post/721919876659363840",
    "validation_errors":
    []
  }
]
